commity/__init__.py
commity/__main__.py
commity/cli.py
commity/config.py
commity/core.py
commity/llm/__init__.py
commity/llm/base.py
commity/llm/factory.py
commity/llm/gemini.py
commity/llm/nvidia.py
commity/llm/ollama.py
commity/llm/openai.py
commity/llm/openrouter.py
commity/utils/__init__.py
commity/utils/commit_cleaner.py
commity/utils/prompt_organizer.py
commity/utils/spinner.py
commity/utils/token_counter.py
commity-0.1.19.dist-info/METADATA
commity-0.1.19.dist-info/WHEEL
commity-0.1.19.dist-info/entry_points.txt
commity-0.1.19.dist-info/licenses/LICENSE
commity-0.1.19.dist-info/RECORD
