Metadata-Version: 2.4
Name: commity
Version: 0.1.19
Summary: Generate intelligent Git commit messages with AI. Supports Conventional Commits, emoji, and multiple LLM providers like OpenAI, Ollama, and Gemini.
Project-URL: Homepage, https://github.com/freboe/commity
Project-URL: Documentation, https://github.com/freboe/commity/blob/main/README.md
Project-URL: Source, https://github.com/freboe/commity
Project-URL: Tracker, https://github.com/freboe/commity/issues
Author: freboe, skyci
License-Expression: GPL-3.0-or-later
License-File: LICENSE
Keywords: ai,commit,commity,conventional-commits,gemini,git,llm,message,ollama,openai
Classifier: Development Status :: 4 - Beta
Classifier: Intended Audience :: Developers
Classifier: License :: OSI Approved :: GNU General Public License v3 (GPLv3)
Classifier: Programming Language :: Python :: 3
Classifier: Programming Language :: Python :: 3.12
Classifier: Topic :: Software Development :: Version Control :: Git
Requires-Python: >=3.12
Requires-Dist: pydantic>=2.12.4
Requires-Dist: requests>=2.32.4
Requires-Dist: rich>=13.7.1
Requires-Dist: tiktoken>=0.11.0
Requires-Dist: unidiff>=0.7.5
